.gitignore
LICENSE
MANIFEST.in
README.rst
setup.cfg
setup.py
internet_sabotage/__init__.py
internet_sabotage/__pycache__/__init__.cpython-39.pyc
internet_sabotage3.egg-info/PKG-INFO
internet_sabotage3.egg-info/SOURCES.txt
internet_sabotage3.egg-info/dependency_links.txt
internet_sabotage3.egg-info/requires.txt
internet_sabotage3.egg-info/top_level.txt