Metadata-Version: 2.1
Name: internet-sabotage3
Version: 0.1.6
Summary: Disable network connection for Testing
Home-page: https://github.com/PetrDlouhy/python-internet-sabotage
Author: André Luiz
Author-email: contato@xdvl.info
License: MIT
Keywords: internet disable unittest
Platform: UNKNOWN
Classifier: Development Status :: 4 - Beta
Classifier: Intended Audience :: Developers
Classifier: License :: OSI Approved :: MIT License
Classifier: Operating System :: OS Independent
Classifier: Programming Language :: Python :: 2
Classifier: Programming Language :: Python :: 3
Classifier: Topic :: Software Development :: Libraries
Classifier: Topic :: Software Development :: Testing
License-File: LICENSE
